mkdocstrings_handlers/twincat/__init__.py
mkdocstrings_handlers/twincat/_internal/__init__.py
mkdocstrings_handlers/twincat/_internal/config.py
mkdocstrings_handlers/twincat/_internal/debug.py
mkdocstrings_handlers/twincat/_internal/handler.py
mkdocstrings_handlers/twincat/_internal/rendering.py
mkdocstrings_handlers/twincat/py.typed
mkdocstrings_handlers/twincat/templates/material/_base/children.html.jinja
mkdocstrings_handlers/twincat/templates/material/_base/documentation.html.jinja
mkdocstrings_handlers/twincat/templates/material/_base/dut.html.jinja
mkdocstrings_handlers/twincat/templates/material/_base/gvl.html.jinja
mkdocstrings_handlers/twincat/templates/material/_base/itf.html.jinja
mkdocstrings_handlers/twincat/templates/material/_base/labels.html.jinja
mkdocstrings_handlers/twincat/templates/material/_base/method.html.jinja
mkdocstrings_handlers/twincat/templates/material/_base/plcproject.html.jinja
mkdocstrings_handlers/twincat/templates/material/_base/pou.html.jinja
mkdocstrings_handlers/twincat/templates/material/_base/property.html.jinja
mkdocstrings_handlers/twincat/templates/material/_base/summary.html.jinja
mkdocstrings_handlers/twincat/templates/material/_base/summary/duts.html.jinja
mkdocstrings_handlers/twincat/templates/material/_base/summary/gvls.html.jinja
mkdocstrings_handlers/twincat/templates/material/_base/summary/itfs.html.jinja
mkdocstrings_handlers/twincat/templates/material/_base/summary/methods.html.jinja
mkdocstrings_handlers/twincat/templates/material/_base/summary/pous.html.jinja
mkdocstrings_handlers/twincat/templates/material/_base/summary/properties.html.jinja
mkdocstrings_handlers/twincat/templates/material/_base/summary/variables.html.jinja
mkdocstrings_handlers/twincat/templates/material/_base/variable.html.jinja
mkdocstrings_handlers/twincat/templates/material/children.html.jinja
mkdocstrings_handlers/twincat/templates/material/documentation.html.jinja
mkdocstrings_handlers/twincat/templates/material/dut.html.jinja
mkdocstrings_twincat-0.3.5.dist-info/METADATA
mkdocstrings_twincat-0.3.5.dist-info/WHEEL
mkdocstrings_twincat-0.3.5.dist-info/entry_points.txt
mkdocstrings_twincat-0.3.5.dist-info/licenses/LICENSE
mkdocstrings_twincat-0.3.5.dist-info/RECORD
