Metadata-Version: 2.4
Name: mkdocstrings-twincat
Version: 0.3.5
Summary: A Twincat handler for mkdocstrings.
Author-Email: drehstromer <privat@samuelruckli.ch>
License-Expression: MIT
License-File: LICENSE
Classifier: Development Status :: 4 - Beta
Classifier: Intended Audience :: Developers
Classifier: Programming Language :: Python
Classifier: Programming Language :: Python :: 3
Classifier: Programming Language :: Python :: 3 :: Only
Classifier: Programming Language :: Python :: 3.9
Classifier: Programming Language :: Python :: 3.10
Classifier: Programming Language :: Python :: 3.11
Classifier: Programming Language :: Python :: 3.12
Classifier: Programming Language :: Python :: 3.13
Classifier: Programming Language :: Python :: 3.14
Classifier: Topic :: Documentation
Classifier: Topic :: Software Development
Classifier: Topic :: Utilities
Classifier: Typing :: Typed
Project-URL: Homepage, https://drehstromer.github.io/mkdocstrings-twincat
Project-URL: Documentation, https://drehstromer.github.io/mkdocstrings-twincat
Project-URL: Changelog, https://drehstromer.github.io/mkdocstrings-twincat/changelog
Project-URL: Repository, https://github.com/drehstromer/mkdocstrings-twincat
Project-URL: Issues, https://github.com/drehstromer/mkdocstrings-twincat/issues
Project-URL: Discussions, https://github.com/drehstromer/mkdocstrings-twincat/discussions
Project-URL: Gitter, https://gitter.im/mkdocstrings-twincat/community
Project-URL: Funding, https://github.com/sponsors/drehstromer
Requires-Python: >=3.11
Requires-Dist: mkdocstrings>=0.18
Requires-Dist: pytwincatparser>=0.5.5
